keli_scoreboard/__init__.py
keli_scoreboard/protocol.py
keli_scoreboard_driver-1.1.0.dist-info/licenses/LICENSE
keli_scoreboard_driver-1.1.0.dist-info/METADATA
keli_scoreboard_driver-1.1.0.dist-info/WHEEL
keli_scoreboard_driver-1.1.0.dist-info/top_level.txt
keli_scoreboard_driver-1.1.0.dist-info/RECORD
